psx-cpu/rtl/cpu32.sv
module r3000a (
    input   logic           clk,
    input   logic           reset,
    output  logic [31:0]    pc
);

    //logic [31:0] pc;
    logic [31:0] next_pc;

    always_comb begin
        next_pc = pc + 4;
    end

    always_ff @(posedge clk) begin
        if(reset)
            pc <= 32'b0;
        else begin
            pc <= next_pc;
        end
    end

endmodule

psx-cpu/waves/pc__test_pc.vcd
$version Generated by VerilatedVcd $end
$timescale 1ps $end
 $scope module TOP $end
  $var wire 1 " clk $end
  $var wire 1 # reset $end
  $var wire 32 $ pc [31:0] $end
  $scope module r3000a $end
   $var wire 1 " clk $end
   $var wire 1 # reset $end
   $var wire 32 $ pc [31:0] $end
   $var wire 32 % next_pc [31:0] $end
  $upscope $end
 $upscope $end
$enddefinitions $end


#0
0"
1#
b00000000000000000000000000000000 $
b00000000000000000000000000000100 %
#1
1"
#2
0"
#3
0#
#4
1"
b00000000000000000000000000000100 $
b00000000000000000000000000001000 %
#5
0"
#7
1"
b00000000000000000000000000001000 $
b00000000000000000000000000001100 %
#8
0"
#10
1"
b00000000000000000000000000001100 $
b00000000000000000000000000010000 %
#11
0"
#13
1"
b00000000000000000000000000010000 $
b00000000000000000000000000010100 %
#14
0"
#16
1"
b00000000000000000000000000010100 $
b00000000000000000000000000011000 %
#17
0"
#19
1"
b00000000000000000000000000011000 $
b00000000000000000000000000011100 %
#20
0"
#22
1"
b00000000000000000000000000011100 $
b00000000000000000000000000100000 %
#23
0"
#25
1"
b00000000000000000000000000100000 $
b00000000000000000000000000100100 %
#26
0"
#28
1"
b00000000000000000000000000100100 $
b00000000000000000000000000101000 %
#29
0"
#31
1"
b00000000000000000000000000101000 $
b00000000000000000000000000101100 %
#32
0"
#34
1"
b00000000000000000000000000101100 $
b00000000000000000000000000110000 %
#35
0"
#37
1"
b00000000000000000000000000110000 $
b00000000000000000000000000110100 %
#38
0"
#40
1"
b00000000000000000000000000110100 $
b00000000000000000000000000111000 %
#41
0"
#43
1"
b00000000000000000000000000111000 $
b00000000000000000000000000111100 %
#44
0"
#46
1"
b00000000000000000000000000111100 $
b00000000000000000000000001000000 %
#47
0"
#49
1"
b00000000000000000000000001000000 $
b00000000000000000000000001000100 %
#50
0"
#52
1"
b00000000000000000000000001000100 $
b00000000000000000000000001001000 %
#53
0"
#55
1"
b00000000000000000000000001001000 $
b00000000000000000000000001001100 %
#56
0"
#58
1"
b00000000000000000000000001001100 $
b00000000000000000000000001010000 %
#59
0"
#61
1"
b00000000000000000000000001010000 $
b00000000000000000000000001010100 %
#62
0"
#64
1"
b00000000000000000000000001010100 $
b00000000000000000000000001011000 %
#65
0"
#67
1"
b00000000000000000000000001011000 $
b00000000000000000000000001011100 %
#68
0"
#70
1"
b00000000000000000000000001011100 $
b00000000000000000000000001100000 %
#71
0"
#73
1"
b00000000000000000000000001100000 $
b00000000000000000000000001100100 %
#74
0"
#76
1"
b00000000000000000000000001100100 $
b00000000000000000000000001101000 %
#77
0"
#78
1#
#79
1"
b00000000000000000000000000000000 $
b00000000000000000000000000000100 %
#80
0"
#82
1"
#83
0"
#84
0#
#85
1"
b00000000000000000000000000000100 $
b00000000000000000000000000001000 %
#86
0"
#88
1"
b00000000000000000000000000001000 $
b00000000000000000000000000001100 %
#89
0"
#91
1"
b00000000000000000000000000001100 $
b00000000000000000000000000010000 %
#92
0"
#94
1"
b00000000000000000000000000010000 $
b00000000000000000000000000010100 %
#95
0"
#97
1"
b00000000000000000000000000010100 $
b00000000000000000000000000011000 %
#98
0"
#100
1"
b00000000000000000000000000011000 $
b00000000000000000000000000011100 %
#101
0"
#103
1"
b00000000000000000000000000011100 $
b00000000000000000000000000100000 %
#104
0"
#106
1"
b00000000000000000000000000100000 $
b00000000000000000000000000100100 %
#107
0"
#109
1"
b00000000000000000000000000100100 $
b00000000000000000000000000101000 %
#110
0"
#112
1"
b00000000000000000000000000101000 $
b00000000000000000000000000101100 %
#113
0"
#115
1"
b00000000000000000000000000101100 $
b00000000000000000000000000110000 %
#116
0"
#118
1"
b00000000000000000000000000110000 $
b00000000000000000000000000110100 %
#119
0"
#121
1"
b00000000000000000000000000110100 $
b00000000000000000000000000111000 %
#122
0"
#124
1"
b00000000000000000000000000111000 $
b00000000000000000000000000111100 %
#125
0"
#127
1"
b00000000000000000000000000111100 $
b00000000000000000000000001000000 %
#128
0"
#130
1"
b00000000000000000000000001000000 $
b00000000000000000000000001000100 %
#131
0"
#133
1"
b00000000000000000000000001000100 $
b00000000000000000000000001001000 %
#134
0"
#136
1"
b00000000000000000000000001001000 $
b00000000000000000000000001001100 %
#137
0"
#139
1"
b00000000000000000000000001001100 $
b00000000000000000000000001010000 %
#140
0"
#142
1"
b00000000000000000000000001010000 $
b00000000000000000000000001010100 %
#143
0"
#145
1"
b00000000000000000000000001010100 $
b00000000000000000000000001011000 %
#146
0"
#148
1"
b00000000000000000000000001011000 $
b00000000000000000000000001011100 %
#149
0"
#151
1"
b00000000000000000000000001011100 $
b00000000000000000000000001100000 %
#152
0"
#154
1"
b00000000000000000000000001100000 $
b00000000000000000000000001100100 %
#155
0"
#157
1"
b00000000000000000000000001100100 $
b00000000000000000000000001101000 %
